cv2_rectangle_around_center/LICENSE
cv2_rectangle_around_center/README.MD
cv2_rectangle_around_center/__init__.py
cv2_rectangle_around_center/requirements.txt
cv2_rectangle_around_center/thirdparty.json
cv2_rectangle_around_center-0.10.dist-info/LICENSE.rst
cv2_rectangle_around_center-0.10.dist-info/METADATA
cv2_rectangle_around_center-0.10.dist-info/WHEEL
cv2_rectangle_around_center-0.10.dist-info/top_level.txt
cv2_rectangle_around_center-0.10.dist-info/RECORD
